fastapi_build/__init__.py
fastapi_build/gunicorn_conf.py
fastapi_build/server.py
fastapi_build/api/__init__.py
fastapi_build/api/urls.py
fastapi_build/api/user.py
fastapi_build/auth/__init__.py
fastapi_build/auth/authentication.py
fastapi_build/auth/base_authentication.py
fastapi_build/auth/base_permission.py
fastapi_build/celery_task/__init__.py
fastapi_build/celery_task/celery_app.py
fastapi_build/celery_task/celery_config.py
fastapi_build/celery_task/enums.py
fastapi_build/celery_task/tasks/__init__.py
fastapi_build/celery_task/tasks/demo.py
fastapi_build/celery_task/utils/__init__.py
fastapi_build/common/__init__.py
fastapi_build/common/load_model.py
fastapi_build/common/log.py
fastapi_build/common/patch/__init__.py
fastapi_build/config/__init__.py
fastapi_build/config/dev.py
fastapi_build/config/settings.py
fastapi_build/core/__init__.py
fastapi_build/core/base_view.py
fastapi_build/core/context.py
fastapi_build/core/decorator.py
fastapi_build/core/response.py
fastapi_build/dao/__init__.py
fastapi_build/dao/base/__init__.py
fastapi_build/dao/base/base_dao.py
fastapi_build/dao/base/database_fetch.py
fastapi_build/dao/base/model_crud.py
fastapi_build/dao/base/queryset.py
fastapi_build/db/__init__.py
fastapi_build/db/database.py
fastapi_build/db/db_url.py
fastapi_build/db/es.py
fastapi_build/db/redis_client.py
fastapi_build/deploy/__init__.py
fastapi_build/exceptions/__init__.py
fastapi_build/exceptions/base.py
fastapi_build/exceptions/custom_exception.py
fastapi_build/exceptions/error_code.py
fastapi_build/exceptions/http_status.py
fastapi_build/middleware/__init__.py
fastapi_build/middleware/middle.py
fastapi_build/middleware/startup.py
fastapi_build/models/__init__.py
fastapi_build/models/base.py
fastapi_build/models/user.py
fastapi_build/scripts/__init__.py
fastapi_build/scripts/add_plugin.py
fastapi_build/scripts/cli.py
fastapi_build/scripts/copy_exclude.py
fastapi_build/scripts/migrate.py
fastapi_build/scripts/remove_header.py
fastapi_build-1.0.4.dist-info/licenses/LICENSE
fastapi_build-1.0.4.dist-info/METADATA
fastapi_build-1.0.4.dist-info/WHEEL
fastapi_build-1.0.4.dist-info/entry_points.txt
fastapi_build-1.0.4.dist-info/top_level.txt
fastapi_build-1.0.4.dist-info/RECORD
